automate_mts/__init__.py
automate_mts/__main__.py
automate_mts-1.0.1.dist-info/METADATA
automate_mts-1.0.1.dist-info/WHEEL
automate_mts-1.0.1.dist-info/entry_points.txt
automate_mts-1.0.1.dist-info/top_level.txt
automate_mts-1.0.1.dist-info/RECORD
