Metadata-Version: 2.4
Name: automate-mts
Version: 1.0.1
Summary: Automatically bundles Cobol documentation into sub-directories based on unique filenames.
Author: Ben Bastianelli
Author-email: benbastianelli@gmail.com
Classifier: Programming Language :: Python :: 3
Classifier: Operating System :: OS Independent
Requires-Python: >=3.6
Dynamic: author
Dynamic: author-email
Dynamic: classifier
Dynamic: requires-python
Dynamic: summary
